Metadata-Version: 2.0
Name: odoo9-addon-l10n-nl-postcodeapi
Version: 9.0.0.1.0
Summary: Autocomplete Dutch addresses using PostcodeApi.nu
Home-page: https://github.com/OCA/l10n-netherlands
Author: Therp BV,Odoo Community Association (OCA)
Author-email: support@odoo-community.org
License: AGPL-3
Platform: UNKNOWN
Classifier: Programming Language :: Python :: 2.7
Classifier: Framework :: Odoo
Classifier: License :: OSI Approved :: GNU Affero General Public License v3
Requires-Dist: odoo (<9.1a,>=9.0a)
Requires-Dist: odoo9-addon-partner-street-number
Requires-Dist: pyPostcode
